INSTALL.rst
LICENSE
MANIFEST.in
README.rst
VERSION
requirements.txt
setup.py
src/transpyler/__init__.py
src/transpyler/__main__.py
src/transpyler/console.py
src/transpyler/curses.py
src/transpyler/errors.py
src/transpyler/info.py
src/transpyler/introspection.py
src/transpyler/lexer.py
src/transpyler/math.py
src/transpyler/namespace.py
src/transpyler/pygments.py
src/transpyler/runners.py
src/transpyler/token.py
src/transpyler/transpyler.py
src/transpyler.egg-info/PKG-INFO
src/transpyler.egg-info/SOURCES.txt
src/transpyler.egg-info/dependency_links.txt
src/transpyler.egg-info/not-zip-safe
src/transpyler.egg-info/requires.txt
src/transpyler.egg-info/top_level.txt
src/transpyler/jupyter/__init__.py
src/transpyler/jupyter/__main__.py
src/transpyler/jupyter/app.py
src/transpyler/jupyter/kernel.py
src/transpyler/jupyter/setup.py
src/transpyler/jupyter/shell.py
src/transpyler/jupyter/assets/kernel.js
src/transpyler/jupyter/assets/logo-32x32.png
src/transpyler/jupyter/assets/logo-64x64.png
src/transpyler/l10n/__init__.py
src/transpyler/l10n/es_BR.mo
src/transpyler/l10n/es_BR.po
src/transpyler/l10n/ko_KR.mo
src/transpyler/l10n/ko_KR.po
src/transpyler/l10n/pt_BR.mo
src/transpyler/l10n/pt_BR.po
src/transpyler/l10n/transpyler.pot
src/transpyler/lib/__init__.py
src/transpyler/lib/_lib_io.py
src/transpyler/lib/_lib_std.py
src/transpyler/lib/_lib_str.py
src/transpyler/translate/__init__.py
src/transpyler/translate/extract.py
src/transpyler/translate/gettext.py
src/transpyler/translate/google_translate.py
src/transpyler/translate/translate.py
src/transpyler/turtle/__init__.py
src/transpyler/turtle/namespace.py
src/transpyler/turtle/state.py
src/transpyler/turtle/stategroup.py
src/transpyler/turtle/tk.py
src/transpyler/turtle/turtle.py
src/transpyler/turtle/turtlegroup.py
src/transpyler/turtle/utils.py
src/transpyler/turtle/data/turtleart.svg
src/transpyler/turtle/qt/__init__.py
src/transpyler/turtle/qt/__main__.py
src/transpyler/turtle/qt/runners.py
src/transpyler/turtle/qt/scene.py
src/transpyler/turtle/qt/state.py
src/transpyler/turtle/qt/utils.py
src/transpyler/turtle/qt/view.py
src/transpyler/utils/__init__.py
src/transpyler/utils/decorators.py
src/transpyler/utils/namespaces.py
