Metadata-Version: 2.1
Name: transpyler
Version: 0.5.0
Summary: A framework for building localized Python-like languages.
Home-page: https://github.com/transpyler/transpyler/
Author: Fábio Macêdo Mendes
Author-email: fabiomacedomendes@gmail.com
License: UNKNOWN
Platform: any
Classifier: Development Status :: 4 - Beta
Classifier: Intended Audience :: Developers
Classifier: License :: OSI Approved :: GNU General Public License (GPL)
Classifier: Operating System :: OS Independent
Classifier: Programming Language :: Python
Classifier: Programming Language :: Python :: 3
Classifier: Programming Language :: Python :: 3.4
Classifier: Programming Language :: Python :: 3.5
Classifier: Programming Language :: Python :: 3.6
Classifier: Topic :: Software Development :: Libraries
Provides-Extra: jupyter
Provides-Extra: dev
Provides-Extra: google_translate
Provides-Extra: pygments
